moduvent/__init__.py
moduvent/async_moduvent.py
moduvent/common.py
moduvent/descriptors.py
moduvent/events.py
moduvent/module_loader.py
moduvent/moduvent.py
moduvent/utils.py
moduvent-5.9.dist-info/licenses/LICENSE
moduvent-5.9.dist-info/METADATA
moduvent-5.9.dist-info/WHEEL
moduvent-5.9.dist-info/top_level.txt
moduvent-5.9.dist-info/RECORD
