Metadata-Version: 2.4
Name: moduvent
Version: 5.9
Summary: A lightweight, modular event system for Python applications with plugin architecture support.
Author-email: Joxos <xujunhao61@163.com>
Requires-Python: >=3.12
License-File: LICENSE
Requires-Dist: loguru>=0.7.3
Dynamic: license-file
